spectrumuncurver/__init__.py
spectrumuncurver/__main__.py
spectrumuncurver/spectrumuncurver.py
spectrumuncurver/test/__init__.py
spectrumuncurver/test/test_spectroCurbatureCorrection.py
spectrumuncurver-0.1.11.dist-info/LICENSE.md
spectrumuncurver-0.1.11.dist-info/METADATA
spectrumuncurver-0.1.11.dist-info/WHEEL
spectrumuncurver-0.1.11.dist-info/top_level.txt
spectrumuncurver-0.1.11.dist-info/RECORD
